automol/__init__.py
automol/amchi/__init__.py
automol/amchi/_assess.py
automol/amchi/_conv.py
automol/amchi/_draw.py
automol/amchi/base/__init__.py
automol/amchi/base/_core.py
automol/chi/__init__.py
automol/chi/_conv.py
automol/chi/base/__init__.py
automol/chi/base/_core.py
automol/combine.py
automol/embed/__init__.py
automol/embed/_cleanup.py
automol/embed/_dgeom.py
automol/embed/_findif.py
automol/error.py
automol/etrans/__init__.py
automol/etrans/_fxn.py
automol/etrans/_par.py
automol/etrans/combine.py
automol/etrans/estimate.py
automol/extern/__init__.py
automol/extern/molfile.py
automol/extern/py3dmol_.py
automol/extern/rdkit_.py
automol/formula/__init__.py
automol/formula/_formula.py
automol/formula/reac.py
automol/geom/__init__.py
automol/geom/_align.py
automol/geom/_conv.py
automol/geom/_extra.py
automol/geom/_pyx2z.py
automol/geom/_ring.py
automol/geom/base/__init__.py
automol/geom/base/_comp.py
automol/geom/base/_core.py
automol/graph/_0embed.py
automol/graph/_1conv.py
automol/graph/__init__.py
automol/graph/base/__init__.py
automol/graph/base/_algo.py
automol/graph/base/_amchi.py
automol/graph/base/_canon.py
automol/graph/base/_core.py
automol/graph/base/_func_group.py
automol/graph/base/_geom.py
automol/graph/base/_heur.py
automol/graph/base/_kekule.py
automol/graph/base/_networkx.py
automol/graph/base/_smiles.py
automol/graph/base/_stereo.py
automol/graph/base/ts.py
automol/graph/vmat.py
automol/graph/zmat.py
automol/inchi/__init__.py
automol/inchi/_assess.py
automol/inchi/_conv.py
automol/inchi/_draw.py
automol/inchi/base/__init__.py
automol/inchi/base/_core.py
automol/inchi_key.py
automol/mult/__init__.py
automol/mult/_mult.py
automol/mult/ts.py
automol/par.py
automol/pot/__init__.py
automol/pot/_fit.py
automol/pot/_intmol.py
automol/pot/_lib.py
automol/pot/_pot.py
automol/pot/_read.py
automol/prop/__init__.py
automol/prop/_wfn.py
automol/prop/freq.py
automol/reac/_0core.py
automol/reac/_1util.py
automol/reac/_2stereo.py
automol/reac/_3find.py
automol-2023.8.0.dist-info/LICENSE
automol-2023.8.0.dist-info/METADATA
automol-2023.8.0.dist-info/WHEEL
automol-2023.8.0.dist-info/RECORD
